AUTHORS
BUGS
COPYING
ChangeLog
INSTALL
MANIFEST.in
Makefile
README
TODO
build.sh
ez_setup.py
setup.cfg
setup.py
elementary/__init__.py
elementary/elementary.c_elementary.c
elementary/elementary.c_elementary.pyx
elementary/elementary.c_elementary_anchorblock.pxi
elementary/elementary.c_elementary_anchorview.pxi
elementary/elementary.c_elementary_background.pxi
elementary/elementary.c_elementary_box.pxi
elementary/elementary.c_elementary_bubble.pxi
elementary/elementary.c_elementary_button.pxi
elementary/elementary.c_elementary_check.pxi
elementary/elementary.c_elementary_clock.pxi
elementary/elementary.c_elementary_entry.pxi
elementary/elementary.c_elementary_fileselector.pxi
elementary/elementary.c_elementary_flip.pxi
elementary/elementary.c_elementary_frame.pxi
elementary/elementary.c_elementary_genlist.pxi
elementary/elementary.c_elementary_hover.pxi
elementary/elementary.c_elementary_hoversel.pxi
elementary/elementary.c_elementary_icon.pxi
elementary/elementary.c_elementary_image.pxi
elementary/elementary.c_elementary_innerwindow.pxi
elementary/elementary.c_elementary_label.pxi
elementary/elementary.c_elementary_layout.pxi
elementary/elementary.c_elementary_list.pxi
elementary/elementary.c_elementary_menu.pxi
elementary/elementary.c_elementary_notepad.pxi
elementary/elementary.c_elementary_notify.pxi
elementary/elementary.c_elementary_object.pxi
elementary/elementary.c_elementary_pager.pxi
elementary/elementary.c_elementary_panel.pxi
elementary/elementary.c_elementary_photo.pxi
elementary/elementary.c_elementary_progressbar.pxi
elementary/elementary.c_elementary_radio.pxi
elementary/elementary.c_elementary_scrolled_entry.pxi
elementary/elementary.c_elementary_scroller.pxi
elementary/elementary.c_elementary_separator.pxi
elementary/elementary.c_elementary_slider.pxi
elementary/elementary.c_elementary_spinner.pxi
elementary/elementary.c_elementary_table.pxi
elementary/elementary.c_elementary_toggle.pxi
elementary/elementary.c_elementary_toolbar.pxi
python_elementary.egg-info/PKG-INFO
python_elementary.egg-info/SOURCES.txt
python_elementary.egg-info/dependency_links.txt
python_elementary.egg-info/not-zip-safe
python_elementary.egg-info/requires.txt
python_elementary.egg-info/top_level.txt
