Metadata-Version: 1.0
Name: python-elementary
Version: 0.7.1
Summary: Python bindings for Elementary
Home-page: http://www.freeesmartphone.org
Author: Simon Busch
Author-email: morphis@gravedo.de
License: LGPL
Keywords: wrapper bindings ui elementary graphics
Platform: UNKNOWN
Classifier: Development Status :: 3 - Alpha
Classifier: Environment :: Console :: Framebuffer
Classifier: Environment :: X11 Applications
Classifier: Intended Audience :: Developers
Classifier: License :: OSI Approved :: GNU Library or Lesser General Public License (LGPL)
Classifier: Operating System :: MacOS :: MacOS X
Classifier: Operating System :: POSIX
Classifier: Programming Language :: C
Classifier: Programming Language :: Python
Classifier: Topic :: Software Development :: Libraries :: Python Modules
Classifier: Topic :: Software Development :: User Interfaces
